 [
  {
  "id": 0,
  "slug": "home",
  "title": "Home"
  },
  {
  "id": 1,
  "slug": "local",
  "title": "Local",
  "public_url": "http://www.scpr.org/local",
  "url": "http://www.scpr.org/local"
  },
  {
  "id": 3,
  "slug": "world",
  "title": "US & World",
  "public_url": "http://www.scpr.org/world",
  "url": "http://www.scpr.org/world"
  },
  {
  "id": 4,
  "slug": "environment",
  "title": "Environment & Science",
  "public_url": "http://www.scpr.org/environment",
  "url": "http://www.scpr.org/environment"
  },
  {
  "id": 5,
  "slug": "politics",
  "title": "Politics",
  "public_url": "http://www.scpr.org/politics",
  "url": "http://www.scpr.org/politics"
  },
  {
  "id": 6,
  "slug": "business",
  "title": "Business & Economy",
  "public_url": "http://www.scpr.org/business",
  "url": "http://www.scpr.org/business"
  },
  {
  "id": 7,
  "slug": "crime",
  "title": "Crime & Justice",
  "public_url": "http://www.scpr.org/crime",
  "url": "http://www.scpr.org/crime"
  },
  {
  "id": 8,
  "slug": "education",
  "title": "Education",
  "public_url": "http://www.scpr.org/education",
  "url": "http://www.scpr.org/education"
  },
  {
  "id": 9,
  "slug": "health",
  "title": "Health",
  "public_url": "http://www.scpr.org/health",
  "url": "http://www.scpr.org/health"
  },
  {
  "id": 15,
  "slug": "arts",
  "title": "Arts & Entertainment",
  "public_url": "http://www.scpr.org/arts",
  "url": "http://www.scpr.org/arts"
  },
  {
  "id": 16,
  "slug": "immigration",
  "title": "Immigration & Emerging Communities",
  "public_url": "http://www.scpr.org/immigration",
  "url": "http://www.scpr.org/immigration"
  }
]